wrapped/__init__.py
wrapped/manova.py
wrapped-0.1.0.dist-info/LICENSE
wrapped-0.1.0.dist-info/WHEEL
wrapped-0.1.0.dist-info/METADATA
wrapped-0.1.0.dist-info/RECORD
