Metadata-Version: 2.1
Name: wrapped
Version: 0.1.0
Summary: Python wrappers for useful R functions.
Home-page: https://v715.github.io
Author: Vivek Gopalakrishnan
Author-email: vgopala4@jh.edu
Classifier: License :: OSI Approved :: MIT License
